{
  "azure.mgmt.alertrulerecommendations": {
    "class_nodes": {
      "AlertRuleRecommendationsMgmtClient": {
        "type": null,
        "methods": {
          "__init__": {
            "parameters": {
              "self": {
                "default": null,
                "param_type": "positional_or_keyword"
              },
              "credential": {
                "default": null,
                "param_type": "positional_or_keyword"
              },
              "subscription_id": {
                "default": null,
                "param_type": "positional_or_keyword"
              },
              "base_url": {
                "default": "none",
                "param_type": "positional_or_keyword"
              },
              "cloud_setting": {
                "default": "none",
                "param_type": "keyword_only"
              },
              "kwargs": {
                "default": null,
                "param_type": "var_keyword"
              }
            },
            "is_async": false,
            "overloads": []
          },
          "close": {
            "parameters": {
              "self": {
                "default": null,
                "param_type": "positional_or_keyword"
              }
            },
            "is_async": false,
            "overloads": []
          }
        },
        "properties": {
          "client_side_validation": {
            "attr_type": false
          },
          "alert_rule_recommendations": {
            "attr_type": "AlertRuleRecommendationsOperations"
          }
        }
      }
    },
    "function_nodes": {}
  },
  "azure.mgmt.alertrulerecommendations.operations": {
    "class_nodes": {
      "AlertRuleRecommendationsOperations": {
        "type": null,
        "methods": {
          "__init__": {
            "parameters": {
              "self": {
                "default": null,
                "param_type": "positional_or_keyword"
              },
              "args": {
                "default": null,
                "param_type": "var_positional"
              },
              "kwargs": {
                "default": null,
                "param_type": "var_keyword"
              }
            },
            "is_async": false,
            "overloads": []
          },
          "list_by_resource": {
            "parameters": {
              "self": {
                "default": null,
                "param_type": "positional_or_keyword"
              },
              "resource_uri": {
                "default": null,
                "param_type": "positional_or_keyword"
              },
              "kwargs": {
                "default": null,
                "param_type": "var_keyword"
              }
            },
            "is_async": false,
            "overloads": []
          },
          "list_by_target_type": {
            "parameters": {
              "self": {
                "default": null,
                "param_type": "positional_or_keyword"
              },
              "target_type": {
                "default": null,
                "param_type": "positional_or_keyword"
              },
              "kwargs": {
                "default": null,
                "param_type": "var_keyword"
              }
            },
            "is_async": false,
            "overloads": []
          }
        },
        "properties": {}
      }
    },
    "function_nodes": {}
  },
  "azure.mgmt.alertrulerecommendations.models": {
    "class_nodes": {
      "AlertRuleRecommendationResource": {
        "type": null,
        "methods": {
          "__init__": {
            "parameters": {
              "self": {
                "default": null,
                "param_type": "positional_or_keyword"
              },
              "alert_rule_type": {
                "default": null,
                "param_type": "keyword_only"
              },
              "display_information": {
                "default": null,
                "param_type": "keyword_only"
              },
              "rule_arm_template": {
                "default": null,
                "param_type": "keyword_only"
              },
              "category": {
                "default": "none",
                "param_type": "keyword_only"
              },
              "kwargs": {
                "default": null,
                "param_type": "var_keyword"
              }
            },
            "is_async": false,
            "overloads": []
          },
          "as_dict": {
            "parameters": {
              "self": {
                "default": null,
                "param_type": "positional_or_keyword"
              },
              "keep_readonly": {
                "default": "bool",
                "param_type": "positional_or_keyword"
              },
              "key_transformer": {
                "default": "attribute_transformer",
                "param_type": "positional_or_keyword"
              },
              "kwargs": {
                "default": null,
                "param_type": "var_keyword"
              }
            },
            "is_async": false,
            "overloads": []
          },
          "deserialize": {
            "parameters": {
              "data": {
                "default": null,
                "param_type": "positional_or_keyword"
              },
              "content_type": {
                "default": "none",
                "param_type": "positional_or_keyword"
              }
            },
            "is_async": false,
            "overloads": []
          },
          "enable_additional_properties_sending": {
            "parameters": {},
            "is_async": false,
            "overloads": []
          },
          "from_dict": {
            "parameters": {
              "data": {
                "default": null,
                "param_type": "positional_or_keyword"
              },
              "key_extractors": {
                "default": "none",
                "param_type": "positional_or_keyword"
              },
              "content_type": {
                "default": "none",
                "param_type": "positional_or_keyword"
              }
            },
            "is_async": false,
            "overloads": []
          },
          "is_xml_model": {
            "parameters": {},
            "is_async": false,
            "overloads": []
          },
          "serialize": {
            "parameters": {
              "self": {
                "default": null,
                "param_type": "positional_or_keyword"
              },
              "keep_readonly": {
                "default": "bool",
                "param_type": "positional_or_keyword"
              },
              "kwargs": {
                "default": null,
                "param_type": "var_keyword"
              }
            },
            "is_async": false,
            "overloads": []
          }
        },
        "properties": {
          "alert_rule_type": {
            "attr_type": "alert_rule_type"
          },
          "category": {
            "attr_type": "category"
          },
          "display_information": {
            "attr_type": "display_information"
          },
          "rule_arm_template": {
            "attr_type": "rule_arm_template"
          },
          "id": {
            "attr_type": null
          },
          "name": {
            "attr_type": null
          },
          "type": {
            "attr_type": null
          },
          "system_data": {
            "attr_type": null
          },
          "additional_properties": {
            "attr_type": null
          }
        }
      },
      "AlertRuleRecommendationsListResponse": {
        "type": null,
        "methods": {
          "__init__": {
            "parameters": {
              "self": {
                "default": null,
                "param_type": "positional_or_keyword"
              },
              "value": {
                "default": null,
                "param_type": "keyword_only"
              },
              "next_link": {
                "default": "none",
                "param_type": "keyword_only"
              },
              "kwargs": {
                "default": null,
                "param_type": "var_keyword"
              }
            },
            "is_async": false,
            "overloads": []
          },
          "as_dict": {
            "parameters": {
              "self": {
                "default": null,
                "param_type": "positional_or_keyword"
              },
              "keep_readonly": {
                "default": "bool",
                "param_type": "positional_or_keyword"
              },
              "key_transformer": {
                "default": "attribute_transformer",
                "param_type": "positional_or_keyword"
              },
              "kwargs": {
                "default": null,
                "param_type": "var_keyword"
              }
            },
            "is_async": false,
            "overloads": []
          },
          "deserialize": {
            "parameters": {
              "data": {
                "default": null,
                "param_type": "positional_or_keyword"
              },
              "content_type": {
                "default": "none",
                "param_type": "positional_or_keyword"
              }
            },
            "is_async": false,
            "overloads": []
          },
          "enable_additional_properties_sending": {
            "parameters": {},
            "is_async": false,
            "overloads": []
          },
          "from_dict": {
            "parameters": {
              "data": {
                "default": null,
                "param_type": "positional_or_keyword"
              },
              "key_extractors": {
                "default": "none",
                "param_type": "positional_or_keyword"
              },
              "content_type": {
                "default": "none",
                "param_type": "positional_or_keyword"
              }
            },
            "is_async": false,
            "overloads": []
          },
          "is_xml_model": {
            "parameters": {},
            "is_async": false,
            "overloads": []
          },
          "serialize": {
            "parameters": {
              "self": {
                "default": null,
                "param_type": "positional_or_keyword"
              },
              "keep_readonly": {
                "default": "bool",
                "param_type": "positional_or_keyword"
              },
              "kwargs": {
                "default": null,
                "param_type": "var_keyword"
              }
            },
            "is_async": false,
            "overloads": []
          }
        },
        "properties": {
          "value": {
            "attr_type": "value"
          },
          "next_link": {
            "attr_type": "next_link"
          },
          "additional_properties": {
            "attr_type": null
          }
        }
      },
      "CreatedByType": {
        "type": "Enum",
        "methods": {},
        "properties": {
          "APPLICATION": "APPLICATION",
          "KEY": "KEY",
          "MANAGED_IDENTITY": "MANAGED_IDENTITY",
          "USER": "USER",
          "capitalize": "capitalize",
          "casefold": "casefold",
          "center": "center",
          "count": "count",
          "encode": "encode",
          "endswith": "endswith",
          "expandtabs": "expandtabs",
          "find": "find",
          "format": "format",
          "format_map": "format_map",
          "index": "index",
          "isalnum": "isalnum",
          "isalpha": "isalpha",
          "isascii": "isascii",
          "isdecimal": "isdecimal",
          "isdigit": "isdigit",
          "isidentifier": "isidentifier",
          "islower": "islower",
          "isnumeric": "isnumeric",
          "isprintable": "isprintable",
          "isspace": "isspace",
          "istitle": "istitle",
          "isupper": "isupper",
          "join": "join",
          "ljust": "ljust",
          "lower": "lower",
          "lstrip": "lstrip",
          "maketrans": "maketrans",
          "partition": "partition",
          "removeprefix": "removeprefix",
          "removesuffix": "removesuffix",
          "replace": "replace",
          "rfind": "rfind",
          "rindex": "rindex",
          "rjust": "rjust",
          "rpartition": "rpartition",
          "rsplit": "rsplit",
          "rstrip": "rstrip",
          "split": "split",
          "splitlines": "splitlines",
          "startswith": "startswith",
          "strip": "strip",
          "swapcase": "swapcase",
          "title": "title",
          "translate": "translate",
          "upper": "upper",
          "zfill": "zfill"
        }
      },
      "ErrorAdditionalInfo": {
        "type": null,
        "methods": {
          "__init__": {
            "parameters": {
              "self": {
                "default": null,
                "param_type": "positional_or_keyword"
              },
              "kwargs": {
                "default": null,
                "param_type": "var_keyword"
              }
            },
            "is_async": false,
            "overloads": []
          },
          "as_dict": {
            "parameters": {
              "self": {
                "default": null,
                "param_type": "positional_or_keyword"
              },
              "keep_readonly": {
                "default": "bool",
                "param_type": "positional_or_keyword"
              },
              "key_transformer": {
                "default": "attribute_transformer",
                "param_type": "positional_or_keyword"
              },
              "kwargs": {
                "default": null,
                "param_type": "var_keyword"
              }
            },
            "is_async": false,
            "overloads": []
          },
          "deserialize": {
            "parameters": {
              "data": {
                "default": null,
                "param_type": "positional_or_keyword"
              },
              "content_type": {
                "default": "none",
                "param_type": "positional_or_keyword"
              }
            },
            "is_async": false,
            "overloads": []
          },
          "enable_additional_properties_sending": {
            "parameters": {},
            "is_async": false,
            "overloads": []
          },
          "from_dict": {
            "parameters": {
              "data": {
                "default": null,
                "param_type": "positional_or_keyword"
              },
              "key_extractors": {
                "default": "none",
                "param_type": "positional_or_keyword"
              },
              "content_type": {
                "default": "none",
                "param_type": "positional_or_keyword"
              }
            },
            "is_async": false,
            "overloads": []
          },
          "is_xml_model": {
            "parameters": {},
            "is_async": false,
            "overloads": []
          },
          "serialize": {
            "parameters": {
              "self": {
                "default": null,
                "param_type": "positional_or_keyword"
              },
              "keep_readonly": {
                "default": "bool",
                "param_type": "positional_or_keyword"
              },
              "kwargs": {
                "default": null,
                "param_type": "var_keyword"
              }
            },
            "is_async": false,
            "overloads": []
          }
        },
        "properties": {
          "type": {
            "attr_type": null
          },
          "info": {
            "attr_type": null
          },
          "additional_properties": {
            "attr_type": null
          }
        }
      },
      "ErrorDetail": {
        "type": null,
        "methods": {
          "__init__": {
            "parameters": {
              "self": {
                "default": null,
                "param_type": "positional_or_keyword"
              },
              "kwargs": {
                "default": null,
                "param_type": "var_keyword"
              }
            },
            "is_async": false,
            "overloads": []
          },
          "as_dict": {
            "parameters": {
              "self": {
                "default": null,
                "param_type": "positional_or_keyword"
              },
              "keep_readonly": {
                "default": "bool",
                "param_type": "positional_or_keyword"
              },
              "key_transformer": {
                "default": "attribute_transformer",
                "param_type": "positional_or_keyword"
              },
              "kwargs": {
                "default": null,
                "param_type": "var_keyword"
              }
            },
            "is_async": false,
            "overloads": []
          },
          "deserialize": {
            "parameters": {
              "data": {
                "default": null,
                "param_type": "positional_or_keyword"
              },
              "content_type": {
                "default": "none",
                "param_type": "positional_or_keyword"
              }
            },
            "is_async": false,
            "overloads": []
          },
          "enable_additional_properties_sending": {
            "parameters": {},
            "is_async": false,
            "overloads": []
          },
          "from_dict": {
            "parameters": {
              "data": {
                "default": null,
                "param_type": "positional_or_keyword"
              },
              "key_extractors": {
                "default": "none",
                "param_type": "positional_or_keyword"
              },
              "content_type": {
                "default": "none",
                "param_type": "positional_or_keyword"
              }
            },
            "is_async": false,
            "overloads": []
          },
          "is_xml_model": {
            "parameters": {},
            "is_async": false,
            "overloads": []
          },
          "serialize": {
            "parameters": {
              "self": {
                "default": null,
                "param_type": "positional_or_keyword"
              },
              "keep_readonly": {
                "default": "bool",
                "param_type": "positional_or_keyword"
              },
              "kwargs": {
                "default": null,
                "param_type": "var_keyword"
              }
            },
            "is_async": false,
            "overloads": []
          }
        },
        "properties": {
          "code": {
            "attr_type": null
          },
          "message": {
            "attr_type": null
          },
          "target": {
            "attr_type": null
          },
          "details": {
            "attr_type": null
          },
          "additional_info": {
            "attr_type": null
          },
          "additional_properties": {
            "attr_type": null
          }
        }
      },
      "ErrorResponse": {
        "type": null,
        "methods": {
          "__init__": {
            "parameters": {
              "self": {
                "default": null,
                "param_type": "positional_or_keyword"
              },
              "error": {
                "default": "none",
                "param_type": "keyword_only"
              },
              "kwargs": {
                "default": null,
                "param_type": "var_keyword"
              }
            },
            "is_async": false,
            "overloads": []
          },
          "as_dict": {
            "parameters": {
              "self": {
                "default": null,
                "param_type": "positional_or_keyword"
              },
              "keep_readonly": {
                "default": "bool",
                "param_type": "positional_or_keyword"
              },
              "key_transformer": {
                "default": "attribute_transformer",
                "param_type": "positional_or_keyword"
              },
              "kwargs": {
                "default": null,
                "param_type": "var_keyword"
              }
            },
            "is_async": false,
            "overloads": []
          },
          "deserialize": {
            "parameters": {
              "data": {
                "default": null,
                "param_type": "positional_or_keyword"
              },
              "content_type": {
                "default": "none",
                "param_type": "positional_or_keyword"
              }
            },
            "is_async": false,
            "overloads": []
          },
          "enable_additional_properties_sending": {
            "parameters": {},
            "is_async": false,
            "overloads": []
          },
          "from_dict": {
            "parameters": {
              "data": {
                "default": null,
                "param_type": "positional_or_keyword"
              },
              "key_extractors": {
                "default": "none",
                "param_type": "positional_or_keyword"
              },
              "content_type": {
                "default": "none",
                "param_type": "positional_or_keyword"
              }
            },
            "is_async": false,
            "overloads": []
          },
          "is_xml_model": {
            "parameters": {},
            "is_async": false,
            "overloads": []
          },
          "serialize": {
            "parameters": {
              "self": {
                "default": null,
                "param_type": "positional_or_keyword"
              },
              "keep_readonly": {
                "default": "bool",
                "param_type": "positional_or_keyword"
              },
              "kwargs": {
                "default": null,
                "param_type": "var_keyword"
              }
            },
            "is_async": false,
            "overloads": []
          }
        },
        "properties": {
          "error": {
            "attr_type": "error"
          },
          "additional_properties": {
            "attr_type": null
          }
        }
      },
      "ProxyResource": {
        "type": null,
        "methods": {
          "__init__": {
            "parameters": {
              "self": {
                "default": null,
                "param_type": "positional_or_keyword"
              },
              "kwargs": {
                "default": null,
                "param_type": "var_keyword"
              }
            },
            "is_async": false,
            "overloads": []
          },
          "as_dict": {
            "parameters": {
              "self": {
                "default": null,
                "param_type": "positional_or_keyword"
              },
              "keep_readonly": {
                "default": "bool",
                "param_type": "positional_or_keyword"
              },
              "key_transformer": {
                "default": "attribute_transformer",
                "param_type": "positional_or_keyword"
              },
              "kwargs": {
                "default": null,
                "param_type": "var_keyword"
              }
            },
            "is_async": false,
            "overloads": []
          },
          "deserialize": {
            "parameters": {
              "data": {
                "default": null,
                "param_type": "positional_or_keyword"
              },
              "content_type": {
                "default": "none",
                "param_type": "positional_or_keyword"
              }
            },
            "is_async": false,
            "overloads": []
          },
          "enable_additional_properties_sending": {
            "parameters": {},
            "is_async": false,
            "overloads": []
          },
          "from_dict": {
            "parameters": {
              "data": {
                "default": null,
                "param_type": "positional_or_keyword"
              },
              "key_extractors": {
                "default": "none",
                "param_type": "positional_or_keyword"
              },
              "content_type": {
                "default": "none",
                "param_type": "positional_or_keyword"
              }
            },
            "is_async": false,
            "overloads": []
          },
          "is_xml_model": {
            "parameters": {},
            "is_async": false,
            "overloads": []
          },
          "serialize": {
            "parameters": {
              "self": {
                "default": null,
                "param_type": "positional_or_keyword"
              },
              "keep_readonly": {
                "default": "bool",
                "param_type": "positional_or_keyword"
              },
              "kwargs": {
                "default": null,
                "param_type": "var_keyword"
              }
            },
            "is_async": false,
            "overloads": []
          }
        },
        "properties": {
          "id": {
            "attr_type": null
          },
          "name": {
            "attr_type": null
          },
          "type": {
            "attr_type": null
          },
          "system_data": {
            "attr_type": null
          },
          "additional_properties": {
            "attr_type": null
          }
        }
      },
      "Resource": {
        "type": null,
        "methods": {
          "__init__": {
            "parameters": {
              "self": {
                "default": null,
                "param_type": "positional_or_keyword"
              },
              "kwargs": {
                "default": null,
                "param_type": "var_keyword"
              }
            },
            "is_async": false,
            "overloads": []
          },
          "as_dict": {
            "parameters": {
              "self": {
                "default": null,
                "param_type": "positional_or_keyword"
              },
              "keep_readonly": {
                "default": "bool",
                "param_type": "positional_or_keyword"
              },
              "key_transformer": {
                "default": "attribute_transformer",
                "param_type": "positional_or_keyword"
              },
              "kwargs": {
                "default": null,
                "param_type": "var_keyword"
              }
            },
            "is_async": false,
            "overloads": []
          },
          "deserialize": {
            "parameters": {
              "data": {
                "default": null,
                "param_type": "positional_or_keyword"
              },
              "content_type": {
                "default": "none",
                "param_type": "positional_or_keyword"
              }
            },
            "is_async": false,
            "overloads": []
          },
          "enable_additional_properties_sending": {
            "parameters": {},
            "is_async": false,
            "overloads": []
          },
          "from_dict": {
            "parameters": {
              "data": {
                "default": null,
                "param_type": "positional_or_keyword"
              },
              "key_extractors": {
                "default": "none",
                "param_type": "positional_or_keyword"
              },
              "content_type": {
                "default": "none",
                "param_type": "positional_or_keyword"
              }
            },
            "is_async": false,
            "overloads": []
          },
          "is_xml_model": {
            "parameters": {},
            "is_async": false,
            "overloads": []
          },
          "serialize": {
            "parameters": {
              "self": {
                "default": null,
                "param_type": "positional_or_keyword"
              },
              "keep_readonly": {
                "default": "bool",
                "param_type": "positional_or_keyword"
              },
              "kwargs": {
                "default": null,
                "param_type": "var_keyword"
              }
            },
            "is_async": false,
            "overloads": []
          }
        },
        "properties": {
          "id": {
            "attr_type": null
          },
          "name": {
            "attr_type": null
          },
          "type": {
            "attr_type": null
          },
          "system_data": {
            "attr_type": null
          },
          "additional_properties": {
            "attr_type": null
          }
        }
      },
      "RuleArmTemplate": {
        "type": null,
        "methods": {
          "__init__": {
            "parameters": {
              "self": {
                "default": null,
                "param_type": "positional_or_keyword"
              },
              "schema": {
                "default": null,
                "param_type": "keyword_only"
              },
              "content_version": {
                "default": null,
                "param_type": "keyword_only"
              },
              "variables": {
                "default": null,
                "param_type": "keyword_only"
              },
              "parameters": {
                "default": null,
                "param_type": "keyword_only"
              },
              "resources": {
                "default": null,
                "param_type": "keyword_only"
              },
              "kwargs": {
                "default": null,
                "param_type": "var_keyword"
              }
            },
            "is_async": false,
            "overloads": []
          },
          "as_dict": {
            "parameters": {
              "self": {
                "default": null,
                "param_type": "positional_or_keyword"
              },
              "keep_readonly": {
                "default": "bool",
                "param_type": "positional_or_keyword"
              },
              "key_transformer": {
                "default": "attribute_transformer",
                "param_type": "positional_or_keyword"
              },
              "kwargs": {
                "default": null,
                "param_type": "var_keyword"
              }
            },
            "is_async": false,
            "overloads": []
          },
          "deserialize": {
            "parameters": {
              "data": {
                "default": null,
                "param_type": "positional_or_keyword"
              },
              "content_type": {
                "default": "none",
                "param_type": "positional_or_keyword"
              }
            },
            "is_async": false,
            "overloads": []
          },
          "enable_additional_properties_sending": {
            "parameters": {},
            "is_async": false,
            "overloads": []
          },
          "from_dict": {
            "parameters": {
              "data": {
                "default": null,
                "param_type": "positional_or_keyword"
              },
              "key_extractors": {
                "default": "none",
                "param_type": "positional_or_keyword"
              },
              "content_type": {
                "default": "none",
                "param_type": "positional_or_keyword"
              }
            },
            "is_async": false,
            "overloads": []
          },
          "is_xml_model": {
            "parameters": {},
            "is_async": false,
            "overloads": []
          },
          "serialize": {
            "parameters": {
              "self": {
                "default": null,
                "param_type": "positional_or_keyword"
              },
              "keep_readonly": {
                "default": "bool",
                "param_type": "positional_or_keyword"
              },
              "kwargs": {
                "default": null,
                "param_type": "var_keyword"
              }
            },
            "is_async": false,
            "overloads": []
          }
        },
        "properties": {
          "schema": {
            "attr_type": "schema"
          },
          "content_version": {
            "attr_type": "content_version"
          },
          "variables": {
            "attr_type": "variables"
          },
          "parameters": {
            "attr_type": "parameters"
          },
          "resources": {
            "attr_type": "resources"
          },
          "additional_properties": {
            "attr_type": null
          }
        }
      },
      "SystemData": {
        "type": null,
        "methods": {
          "__init__": {
            "parameters": {
              "self": {
                "default": null,
                "param_type": "positional_or_keyword"
              },
              "created_by": {
                "default": "none",
                "param_type": "keyword_only"
              },
              "created_by_type": {
                "default": "none",
                "param_type": "keyword_only"
              },
              "created_at": {
                "default": "none",
                "param_type": "keyword_only"
              },
              "last_modified_by": {
                "default": "none",
                "param_type": "keyword_only"
              },
              "last_modified_by_type": {
                "default": "none",
                "param_type": "keyword_only"
              },
              "last_modified_at": {
                "default": "none",
                "param_type": "keyword_only"
              },
              "kwargs": {
                "default": null,
                "param_type": "var_keyword"
              }
            },
            "is_async": false,
            "overloads": []
          },
          "as_dict": {
            "parameters": {
              "self": {
                "default": null,
                "param_type": "positional_or_keyword"
              },
              "keep_readonly": {
                "default": "bool",
                "param_type": "positional_or_keyword"
              },
              "key_transformer": {
                "default": "attribute_transformer",
                "param_type": "positional_or_keyword"
              },
              "kwargs": {
                "default": null,
                "param_type": "var_keyword"
              }
            },
            "is_async": false,
            "overloads": []
          },
          "deserialize": {
            "parameters": {
              "data": {
                "default": null,
                "param_type": "positional_or_keyword"
              },
              "content_type": {
                "default": "none",
                "param_type": "positional_or_keyword"
              }
            },
            "is_async": false,
            "overloads": []
          },
          "enable_additional_properties_sending": {
            "parameters": {},
            "is_async": false,
            "overloads": []
          },
          "from_dict": {
            "parameters": {
              "data": {
                "default": null,
                "param_type": "positional_or_keyword"
              },
              "key_extractors": {
                "default": "none",
                "param_type": "positional_or_keyword"
              },
              "content_type": {
                "default": "none",
                "param_type": "positional_or_keyword"
              }
            },
            "is_async": false,
            "overloads": []
          },
          "is_xml_model": {
            "parameters": {},
            "is_async": false,
            "overloads": []
          },
          "serialize": {
            "parameters": {
              "self": {
                "default": null,
                "param_type": "positional_or_keyword"
              },
              "keep_readonly": {
                "default": "bool",
                "param_type": "positional_or_keyword"
              },
              "kwargs": {
                "default": null,
                "param_type": "var_keyword"
              }
            },
            "is_async": false,
            "overloads": []
          }
        },
        "properties": {
          "created_by": {
            "attr_type": "created_by"
          },
          "created_by_type": {
            "attr_type": "created_by_type"
          },
          "created_at": {
            "attr_type": "created_at"
          },
          "last_modified_by": {
            "attr_type": "last_modified_by"
          },
          "last_modified_by_type": {
            "attr_type": "last_modified_by_type"
          },
          "last_modified_at": {
            "attr_type": "last_modified_at"
          },
          "additional_properties": {
            "attr_type": null
          }
        }
      }
    },
    "function_nodes": {}
  },
  "azure.mgmt.alertrulerecommendations.aio": {
    "class_nodes": {
      "AlertRuleRecommendationsMgmtClient": {
        "type": null,
        "methods": {
          "__init__": {
            "parameters": {
              "self": {
                "default": null,
                "param_type": "positional_or_keyword"
              },
              "credential": {
                "default": null,
                "param_type": "positional_or_keyword"
              },
              "subscription_id": {
                "default": null,
                "param_type": "positional_or_keyword"
              },
              "base_url": {
                "default": "none",
                "param_type": "positional_or_keyword"
              },
              "cloud_setting": {
                "default": "none",
                "param_type": "keyword_only"
              },
              "kwargs": {
                "default": null,
                "param_type": "var_keyword"
              }
            },
            "is_async": false,
            "overloads": []
          },
          "close": {
            "parameters": {
              "self": {
                "default": null,
                "param_type": "positional_or_keyword"
              }
            },
            "is_async": true,
            "overloads": []
          }
        },
        "properties": {
          "client_side_validation": {
            "attr_type": false
          },
          "alert_rule_recommendations": {
            "attr_type": "AlertRuleRecommendationsOperations"
          }
        }
      }
    },
    "function_nodes": {}
  },
  "azure.mgmt.alertrulerecommendations.aio.operations": {
    "class_nodes": {
      "AlertRuleRecommendationsOperations": {
        "type": null,
        "methods": {
          "__init__": {
            "parameters": {
              "self": {
                "default": null,
                "param_type": "positional_or_keyword"
              },
              "args": {
                "default": null,
                "param_type": "var_positional"
              },
              "kwargs": {
                "default": null,
                "param_type": "var_keyword"
              }
            },
            "is_async": false,
            "overloads": []
          },
          "list_by_resource": {
            "parameters": {
              "self": {
                "default": null,
                "param_type": "positional_or_keyword"
              },
              "resource_uri": {
                "default": null,
                "param_type": "positional_or_keyword"
              },
              "kwargs": {
                "default": null,
                "param_type": "var_keyword"
              }
            },
            "is_async": false,
            "overloads": []
          },
          "list_by_target_type": {
            "parameters": {
              "self": {
                "default": null,
                "param_type": "positional_or_keyword"
              },
              "target_type": {
                "default": null,
                "param_type": "positional_or_keyword"
              },
              "kwargs": {
                "default": null,
                "param_type": "var_keyword"
              }
            },
            "is_async": false,
            "overloads": []
          }
        },
        "properties": {}
      }
    },
    "function_nodes": {}
  }
}